platinum2/__init__.py
platinum2/chromium.py
platinum2/console.py
platinum2/constants.py
platinum2/exceptions.py
platinum2/user_agent.py
platinum2/data/android_build.json
platinum2/data/android_dev.json
platinum2/data/ios.json
platinum2/data/opera_build.json
platinum2-1.5.2.dist-info/LICENSE
platinum2-1.5.2.dist-info/METADATA
platinum2-1.5.2.dist-info/WHEEL
platinum2-1.5.2.dist-info/entry_points.txt
platinum2-1.5.2.dist-info/top_level.txt
platinum2-1.5.2.dist-info/RECORD
