Metadata-Version: 2.1
Name: platinum2
Version: 1.5.2
Summary: Frequently used google chrome commands mappings. A User-Agent generator. All for automation.
Home-page: https://github.com/starsoft35/platinum2
Author: Zhou Ping
Author-email: b2b35@126.com
License: Apache 2.0
Keywords: chromium,automation,testing,user-agent
Classifier: Intended Audience :: Developers
Classifier: License :: OSI Approved :: Apache Software License
Classifier: Operating System :: OS Independent
Classifier: Programming Language :: Python :: 2.7
Classifier: Programming Language :: Python :: 3.3
Classifier: Programming Language :: Python :: 3.4
Classifier: Programming Language :: Python :: 3.5
Classifier: Programming Language :: Python :: 3.6
Classifier: Programming Language :: Python :: 3.7
Classifier: Programming Language :: Python :: Implementation :: CPython
Classifier: Programming Language :: Python :: Implementation :: PyPy
Classifier: Topic :: Software Development :: Testing
Classifier: Topic :: Software Development :: Libraries
Classifier: Topic :: Internet :: WWW/HTTP
License-File: LICENSE
Requires-Dist: six
